odoo/addons/base_rest_datamodel/README.rst
odoo/addons/base_rest_datamodel/__init__.py
odoo/addons/base_rest_datamodel/__manifest__.py
odoo/addons/base_rest_datamodel/restapi.py
odoo/addons/base_rest_datamodel/i18n/base_rest_datamodel.pot
odoo/addons/base_rest_datamodel/i18n/es.po
odoo/addons/base_rest_datamodel/readme/CONTRIBUTORS.rst
odoo/addons/base_rest_datamodel/readme/DESCRIPTION.rst
odoo/addons/base_rest_datamodel/readme/USAGE.rst
odoo/addons/base_rest_datamodel/static/description/icon.png
odoo/addons/base_rest_datamodel/static/description/index.html
odoo/addons/base_rest_datamodel/tests/__init__.py
odoo/addons/base_rest_datamodel/tests/test_from_params.py
odoo/addons/base_rest_datamodel/tests/test_response.py
odoo13_addon_base_rest_datamodel-13.0.3.1.1.dist-info/METADATA
odoo13_addon_base_rest_datamodel-13.0.3.1.1.dist-info/WHEEL
odoo13_addon_base_rest_datamodel-13.0.3.1.1.dist-info/top_level.txt
odoo13_addon_base_rest_datamodel-13.0.3.1.1.dist-info/RECORD
